cobotar_protocol/__init__.py
cobotar_protocol/ar/v1/action_info_pb2.py
cobotar_protocol/ar/v1/action_info_pb2.pyi
cobotar_protocol/ar/v1/action_pb2.py
cobotar_protocol/ar/v1/action_pb2.pyi
cobotar_protocol/ar/v1/ar_config_pb2.py
cobotar_protocol/ar/v1/ar_config_pb2.pyi
cobotar_protocol/ar/v1/assets_pb2.py
cobotar_protocol/ar/v1/assets_pb2.pyi
cobotar_protocol/ar/v1/authoring_action_pb2.py
cobotar_protocol/ar/v1/authoring_action_pb2.pyi
cobotar_protocol/ar/v1/authoring_ar_config_pb2.py
cobotar_protocol/ar/v1/authoring_ar_config_pb2.pyi
cobotar_protocol/ar/v1/authoring_environment_pb2.py
cobotar_protocol/ar/v1/authoring_environment_pb2.pyi
cobotar_protocol/ar/v1/authoring_feedback_pb2.py
cobotar_protocol/ar/v1/authoring_feedback_pb2.pyi
cobotar_protocol/ar/v1/authoring_mapping_pb2.py
cobotar_protocol/ar/v1/authoring_mapping_pb2.pyi
cobotar_protocol/ar/v1/authoring_marker_pb2.py
cobotar_protocol/ar/v1/authoring_marker_pb2.pyi
cobotar_protocol/ar/v1/config_load_pb2.py
cobotar_protocol/ar/v1/config_load_pb2.pyi
cobotar_protocol/ar/v1/environment_pb2.py
cobotar_protocol/ar/v1/environment_pb2.pyi
cobotar_protocol/ar/v1/events_pb2.py
cobotar_protocol/ar/v1/events_pb2.pyi
cobotar_protocol/ar/v1/feedback_info_pb2.py
cobotar_protocol/ar/v1/feedback_info_pb2.pyi
cobotar_protocol/ar/v1/feedback_pb2.py
cobotar_protocol/ar/v1/feedback_pb2.pyi
cobotar_protocol/ar/v1/helper_info_pb2.py
cobotar_protocol/ar/v1/helper_info_pb2.pyi
cobotar_protocol/ar/v1/helper_pb2.py
cobotar_protocol/ar/v1/helper_pb2.pyi
cobotar_protocol/ar/v1/mapping_pb2.py
cobotar_protocol/ar/v1/mapping_pb2.pyi
cobotar_protocol/ar/v1/marker_pb2.py
cobotar_protocol/ar/v1/marker_pb2.pyi
cobotar_protocol/ar/v1/property_pb2.py
cobotar_protocol/ar/v1/property_pb2.pyi
cobotar_protocol/ar/v1/robots_pb2.py
cobotar_protocol/ar/v1/robots_pb2.pyi
cobotar_protocol/ar/v1/template_pb2.py
cobotar_protocol/ar/v1/template_pb2.pyi
cobotar_protocol/ar/v1/worker_pb2.py
cobotar_protocol/ar/v1/worker_pb2.pyi
cobotar_protocol-0.12.3.dist-info/METADATA
cobotar_protocol-0.12.3.dist-info/WHEEL
cobotar_protocol-0.12.3.dist-info/RECORD
