Metadata-Version: 2.4
Name: cobotar-protocol
Version: 0.12.3
Summary: Protocol and more for the cobotar project
Project-URL: Homepage, https://cobotar.org
Project-URL: Documentation, https://cobotar.org/protocol
Project-URL: Repository, https://github.com/cobotar/protocol.git
Project-URL: Bug Tracker, https://github.com/cobotar/protocol/issues
Project-URL: Changelog, https://github.com/cobotar/protocol/blob/master/CHANGELOG.md
Author-email: Rasmus Lunding <rsl@cs.au.dk>
Maintainer-email: Rasmus Lunding <rsl@cs.au.dk>
Keywords: ar,cobot,protocol
Classifier: Programming Language :: Python
Requires-Python: >=3.8
